odoo/addons/product_order_noname/README.rst
odoo/addons/product_order_noname/__init__.py
odoo/addons/product_order_noname/__manifest__.py
odoo/addons/product_order_noname/i18n/es.po
odoo/addons/product_order_noname/i18n/fr.po
odoo/addons/product_order_noname/i18n/it.po
odoo/addons/product_order_noname/i18n/product_order_noname.pot
odoo/addons/product_order_noname/models/__init__.py
odoo/addons/product_order_noname/models/product.py
odoo/addons/product_order_noname/models/product_template.py
odoo/addons/product_order_noname/readme/CONTRIBUTORS.rst
odoo/addons/product_order_noname/readme/CREDITS.rst
odoo/addons/product_order_noname/readme/DESCRIPTION.rst
odoo/addons/product_order_noname/readme/USAGE.rst
odoo/addons/product_order_noname/static/description/icon.png
odoo/addons/product_order_noname/static/description/index.html
odoo_addon_product_order_noname-15.0.1.0.0.8.dist-info/METADATA
odoo_addon_product_order_noname-15.0.1.0.0.8.dist-info/WHEEL
odoo_addon_product_order_noname-15.0.1.0.0.8.dist-info/top_level.txt
odoo_addon_product_order_noname-15.0.1.0.0.8.dist-info/RECORD
